[{"name":"Potato","slug":"potato-funny","emoji":"🥔","imageUrl":"https://upload.wikimedia.org/wikipedia/commons/a/ab/Patates.jpg","tags":["starchy","round","comfort"]},{"name":"Tomato","slug":"tomato-funny","emoji":"🍅","imageUrl":"https://upload.wikimedia.org/wikipedia/commons/8/89/Tomato_je.jpg","tags":["red","juicy","salad"]},{"name":"Carrot","slug":"carrot-funny","emoji":"🥕","imageUrl":"https://upload.wikimedia.org/wikipedia/commons/3/32/CarrotDiversityLg.jpg","tags":["orange","crunchy","healthy"]},{"name":"Onion","slug":"onion-funny","emoji":"🧅","imageUrl":"https://upload.wikimedia.org/wikipedia/commons/2/25/Onion_on_White.JPG","tags":["layered","aromatic","kitchen"]},{"name":"Pumpkin","slug":"pumpkin-funny","emoji":"🎃","imageUrl":"https://upload.wikimedia.org/wikipedia/commons/5/5c/Fairytale_pumpkin.jpg","tags":["autumn","round","festive"]},{"name":"Banana","slug":"banana-funny","emoji":"🍌","imageUrl":"https://upload.wikimedia.org/wikipedia/commons/8/8a/Banana-Single.jpg","tags":["curved","yellow","tropical"]},{"name":"Broccoli","slug":"broccoli-funny","emoji":"🥦","imageUrl":"https://upload.wikimedia.org/wikipedia/commons/0/03/Broccoli_and_cross_section_edit.jpg","tags":["green","tree","healthy"]},{"name":"Eggplant","slug":"eggplant-funny","emoji":"🍆","imageUrl":"https://upload.wikimedia.org/wikipedia/commons/7/7b/Aubergine.jpg","tags":["purple","shiny","veggie"]},{"name":"Panda","slug":"panda-funny","emoji":"🐼","imageUrl":"https://upload.wikimedia.org/wikipedia/commons/0/0f/Grosser_Panda.JPG","tags":["fluffy","bamboo","cute"]},{"name":"Cat","slug":"cat-funny","emoji":"🐱","imageUrl":"https://upload.wikimedia.org/wikipedia/commons/4/4d/Cat_November_2010-1a.jpg","tags":["whiskers","sassy","meme"]},{"name":"Koala","slug":"koala-funny","emoji":"🐨","imageUrl":"https://upload.wikimedia.org/wikipedia/commons/4/49/Koala_climbing_tree.jpg","tags":["sleepy","fluffy","australia"]},{"name":"Duck","slug":"duck-funny","emoji":"🦆","imageUrl":"https://upload.wikimedia.org/wikipedia/commons/b/bf/Peeking_duck.jpg","tags":["quack","waddle","pond"]},{"name":"Owl","slug":"owl-funny","emoji":"🦉","imageUrl":"https://upload.wikimedia.org/wikipedia/commons/5/56/Great_Horned_Owl_01.jpg","tags":["wise","night","staring"]},{"name":"Sloth","slug":"sloth-funny","emoji":"🦥","imageUrl":"https://upload.wikimedia.org/wikipedia/commons/1/18/Bradypus.jpg","tags":["slow","chill","hanging"]},{"name":"Avocado","slug":"avocado-funny","emoji":"🥑","imageUrl":"https://upload.wikimedia.org/wikipedia/commons/7/70/Avocado_fruit.jpg","tags":["millennial","green","toast"]},{"name":"Watermelon","slug":"watermelon-funny","emoji":"🍉","imageUrl":"https://upload.wikimedia.org/wikipedia/commons/4/47/Taiwan_2009_Tainan_City_Organic_Farm_Watermelon_FRD_7962.jpg","tags":["summer","juicy","picnic"]},{"name":"Pineapple","slug":"pineapple-funny","emoji":"🍍","imageUrl":"https://upload.wikimedia.org/wikipedia/commons/c/cb/Pineapple_and_cross_section.jpg","tags":["tropical","spiky","sweet"]},{"name":"Mushroom","slug":"mushroom-funny","emoji":"🍄","imageUrl":"https://upload.wikimedia.org/wikipedia/commons/3/32/Fungi_in_Slovakia.jpg","tags":["fungi","forest","earthy"]},{"name":"Penguin","slug":"penguin-funny","emoji":"🐧","imageUrl":"https://upload.wikimedia.org/wikipedia/commons/0/07/Emperor_Penguin_Molt.jpg","tags":["waddle","antarctic","formal"]},{"name":"Llama","slug":"llama-funny","emoji":"🦙","imageUrl":"https://upload.wikimedia.org/wikipedia/commons/b/b1/Llama_on_Lake_Salinas.jpg","tags":["fluffy","andes","spit"]}]